KuroCloudDicom/__init__.py
KuroCloudDicom/CloudDicomHandlers/ChunkedDicomData.py
KuroCloudDicom/CloudDicomHandlers/CloudDicomDataManager.py
KuroCloudDicom/CloudDicomHandlers/CloudDicomOperations.py
KuroCloudDicom/CloudDicomHandlers/Preprocessor.py
KuroCloudDicom/CloudDicomHandlers/SubareaFullParallelParameters.py
KuroCloudDicom/CloudDicomHandlers/SubareaParameters.py
KuroCloudDicom/CloudDicomHandlers/__init__.py
KuroCloudDicom/DicomHandlers/DicomDataManager.py
KuroCloudDicom/DicomHandlers/DicomOperations.py
KuroCloudDicom/DicomHandlers/SubareaParameters.py
KuroCloudDicom/DicomHandlers/__init__.py
KuroCloudDicom-0.0.2.dist-info/METADATA
KuroCloudDicom-0.0.2.dist-info/WHEEL
KuroCloudDicom-0.0.2.dist-info/top_level.txt
KuroCloudDicom-0.0.2.dist-info/RECORD
